vps/__init__.py
vps/ovhclient.py
vps-0.0.8.dist-info/LICENSE
vps-0.0.8.dist-info/METADATA
vps-0.0.8.dist-info/WHEEL
vps-0.0.8.dist-info/dependency_links.txt
vps-0.0.8.dist-info/top_level.txt
vps-0.0.8.dist-info/RECORD
