Metadata-Version: 2.1
Name: vps
Version: 0.0.8
Summary: Create and Manage VPS Instances
Home-page: https://gitlab.com/aschult5/vps
Author: Andrew Schultz
Author-email: andrew.schultz@protonmail.com
License: UNKNOWN
Platform: UNKNOWN
Classifier: Programming Language :: Python :: 2.7
Classifier: License :: OSI Approved :: MIT License
Classifier: Operating System :: OS Independent
Requires-Dist: ovh (==0.4.8.1)
